general/__init__.py
general/db/__init__.py
general/db/influxdb/__init__.py
general/db/influxdb/influx_handler.py
general/db/mongodb/__init__.py
general/db/mongodb/mongo_handler.py
general/exchange/__init__.py
general/exchange/exchange_factory.py
general/exchange/exchange_handler.py
general/exchange/type_enum.py
general/exchange/binance_um/__init__.py
general/exchange/binance_um/binanceum_handler.py
general/exchange/binance_um/utils.py
general/exchange/okx/__init__.py
general/exchange/okx/okx_handler.py
general/exchange/okx/utils.py
general/exchange/schema/__init__.py
general/exchange/schema/order.py
general/exchange/schema/orderbook.py
general/exchange/schema/trade_recorder.py
general/mutithread/__init__.py
general/mutithread/parallelism.py
general/mutithread/threadpool.py
general/pubsub/__init__.py
general/pubsub/redis_pubsub_handler.py
general/queue/__init__.py
general/queue/redis_queue_hander.py
general/utils/__init__.py
general/utils/read_file.py
general/utils/time.py
coin_infra-4.2.5.dist-info/METADATA
coin_infra-4.2.5.dist-info/WHEEL
coin_infra-4.2.5.dist-info/top_level.txt
coin_infra-4.2.5.dist-info/RECORD
