Metadata-Version: 2.1
Name: coin-infra
Version: 4.2.5
Summary: infra of coin projects
Author: Yi Te
Author-email: coastq22889@icloud.com
Requires-Dist: pymongo
Requires-Dist: redis
Requires-Dist: requests
Requires-Dist: websockets
Requires-Dist: binance-futures-connector
Requires-Dist: python-okx
Requires-Dist: influxdb-client
